test_myp/__init__.py
test_myp/version.py
test_myp-0.1.6.dist-info/METADATA
test_myp-0.1.6.dist-info/WHEEL
test_myp-0.1.6.dist-info/RECORD
