Metadata-Version: 2.1
Name: test-myp
Version: 0.1.6
Summary: 
Author: CrystalWindSnake
Author-email: 568166495@qq.com
Requires-Python: >=3.8,<4.0
Classifier: Programming Language :: Python :: 3
Classifier: Programming Language :: Python :: 3.8
Classifier: Programming Language :: Python :: 3.9
Classifier: Programming Language :: Python :: 3.10
Classifier: Programming Language :: Python :: 3.11
Requires-Dist: nicegui (>=1.4.26,<2.0.0)
